{
  "link": "https://github.com/1syo/wercker-step-gitter-notify",
  "type": "repository",
  "parsedTimestamp": "2025-11-07T10:02:48.335185",
  "output": {
    "name": "wercker-step-gitter-notify",
    "applicationCategory": [
      "Software development"
    ],
    "citation": null,
    "codeRepository": [
      "https://github.com/1syo/wercker-step-gitter-notify"
    ],
    "conditionsOfAccess": null,
    "dateCreated": "2014-05-15",
    "datePublished": "2016-04-01",
    "description": "The step-gitter-notify is a plugin that notifies Gitter.",
    "featureList": [
      "Notify Gitter rooms",
      "Integrate with Wercker pipelines",
      "Configurable notification triggers"
    ],
    "image": null,
    "isAccessibleForFree": true,
    "isBasedOn": null,
    "isPluginModuleOf": null,
    "license": "https://spdx.org/licenses/MIT.html",
    "author": [
      {
        "type": "Person",
        "name": "Kazunari Takahashi",
        "email": null,
        "orcid": null,
        "gitAuthorIds": [],
        "affiliations": [
          "RubyMotionJP",
          "yokohamarb"
        ],
        "currentAffiliation": "RubyMotionJP",
        "affiliationHistory": [],
        "contributionSummary": "Author and maintainer of the Wercker Gitter notification step plugin.",
        "biography": null,
        "academicCatalogRelations": []
      }
    ],
    "operatingSystem": [
      "Linux"
    ],
    "programmingLanguage": [
      "Shell"
    ],
    "softwareRequirements": [
      "Wercker CLI",
      "Gitter token"
    ],
    "processorRequirements": null,
    "memoryRequirements": null,
    "requiresGPU": null,
    "supportingData": [],
    "url": "https://github.com/1syo/wercker-step-gitter-notify",
    "identifier": null,
    "hasAcknowledgements": null,
    "hasDocumentation": "https://github.com/1syo/wercker-step-gitter-notify/blob/master/README.md",
    "hasExecutableInstructions": "https://github.com/1syo/wercker-step-gitter-notify/blob/master/README.md",
    "hasExecutableNotebook": [],
    "readme": "https://github.com/1syo/wercker-step-gitter-notify/blob/master/README.md",
    "hasFunding": [],
    "hasSoftwareImage": [
      {
        "name": "1syo/gitter-notify",
        "description": "Wercker step for notifying Gitter",
        "softwareVersion": "0.0.1",
        "availableInRegistry": "https://hub.wercker.com/steps/1syo/gitter-notify"
      }
    ],
    "imagingModality": null,
    "discipline": [
      "Computer engineering"
    ],
    "disciplineJustification": [
      "Plugin automates CI/CD processes, relevant to software engineering/computer engineering."
    ],
    "relatedDatasets": [],
    "relatedPublications": [],
    "relatedModels": [],
    "relatedAPIs": [
      "https://developer.gitter.im/docs"
    ],
    "relatedToOrganizations": [
      "RubyMotionJP",
      "Yokohama Ruby Brigade",
      {
        "type": "Organization",
        "legalName": "RubyMotionJP",
        "hasRorId": null,
        "alternateNames": [
          "RubyMotion JP"
        ],
        "organizationType": "User Group",
        "parentOrganization": null,
        "country": "Japan",
        "website": null,
        "attributionConfidence": 0.5,
        "academicCatalogRelations": null
      },
      {
        "type": "Organization",
        "legalName": "Yokohama Ruby Brigade",
        "hasRorId": null,
        "alternateNames": [
          "yokohamarb"
        ],
        "organizationType": "User Group",
        "parentOrganization": null,
        "country": "Japan",
        "website": null,
        "attributionConfidence": 0.5,
        "academicCatalogRelations": null
      }
    ],
    "relatedToOrganizationJustification": [
      "Affiliations extracted from GitHub user metadata."
    ],
    "repositoryType": "software",
    "repositoryTypeJustification": [
      "Contains source code for a Wercker CI/CD plugin written in shell script."
    ],
    "relatedToEPFL": false,
    "relatedToEPFLConfidence": 0.0,
    "relatedToEPFLJustification": "After thorough review of all available data for the repository 'wercker-step-gitter-notify', no evidence was found linking the repository, its author, affiliations, organizations, README content, git commits, ORCID records, or related organizations to EPFL or SDSC. Therefore, the cumulative confidence score is 0.0, below the 0.5 threshold for EPFL affiliation.",
    "gitAuthors": [
      {
        "name": "TAKAHASHI Kazunari",
        "email": "takahashi@1syo.net",
        "commits": {
          "total": 1,
          "firstCommitDate": "2014-05-16",
          "lastCommitDate": "2014-05-16"
        }
      }
    ],
    "academicCatalogRelations": []
  },
  "stats": {
    "agent_input_tokens": 0,
    "agent_output_tokens": 0,
    "total_tokens": 0,
    "estimated_input_tokens": 11220,
    "estimated_output_tokens": 1235,
    "estimated_total_tokens": 12455,
    "duration": 145.978521,
    "start_time": "2025-11-07T10:00:22.356212",
    "end_time": "2025-11-07T10:02:48.334733",
    "status_code": 200,
    "github_rate_limit": 5000,
    "github_rate_remaining": 4920,
    "github_rate_reset": "2025-11-07T10:58:02"
  }
}